yadm/__init__.py
yadm/abc.py
yadm/aggregation.py
yadm/bulk.py
yadm/bulk_writer.py
yadm/cache.py
yadm/common.py
yadm/database.py
yadm/document_item.py
yadm/documents.py
yadm/exceptions.py
yadm/join.py
yadm/log_items.py
yadm/markers.py
yadm/queryset.py
yadm/results.py
yadm/serialize.py
yadm/testing.py
yadm/aio/__init__.py
yadm/aio/aggregation.py
yadm/aio/bulk_writer.py
yadm/aio/database.py
yadm/aio/queryset.py
yadm/aio/testing.py
yadm/fields/__init__.py
yadm/fields/base.py
yadm/fields/containers.py
yadm/fields/datetime.py
yadm/fields/decimal.py
yadm/fields/email.py
yadm/fields/embedded.py
yadm/fields/enum.py
yadm/fields/geo.py
yadm/fields/list.py
yadm/fields/map.py
yadm/fields/mongo_map.py
yadm/fields/reference.py
yadm/fields/references_list.py
yadm/fields/set.py
yadm/fields/simple.py
yadm/fields/money/__init__.py
yadm/fields/money/currency.py
yadm/fields/money/money.py
yadm-2.0.9.dist-info/LICENSE
yadm-2.0.9.dist-info/METADATA
yadm-2.0.9.dist-info/WHEEL
yadm-2.0.9.dist-info/top_level.txt
yadm-2.0.9.dist-info/RECORD
