Metadata-Version: 2.1
Name: yadm
Version: 2.0.9
Summary: Yet Another Document Mapper (ODM) for MongoDB
Home-page: https://github.com/zzzsochi/yadm
Author: Zelenyak "ZZZ" Alexander
Author-email: zzz.sochi@gmail.com
License: MIT
Platform: any
Classifier: Development Status :: 5 - Production/Stable
Classifier: Topic :: Database
Classifier: Intended Audience :: Developers
Classifier: Operating System :: OS Independent
Classifier: Programming Language :: Python :: 3
License-File: LICENSE
Requires-Dist: pymongo >=3.7.0
Requires-Dist: zope.dottedname
Requires-Dist: python-dateutil
Requires-Dist: pytz
Requires-Dist: Faker
Provides-Extra: asyncio
Requires-Dist: motor >=2.0.0 ; extra == 'asyncio'
Provides-Extra: test
Requires-Dist: pytest ; extra == 'test'
Requires-Dist: pytest-asyncio ; extra == 'test'
Requires-Dist: pytest-cov ; extra == 'test'
Requires-Dist: coveralls ; extra == 'test'
